{
  "project": "Fix Empty State Messages",
  "branchName": "ralph/empty-state-fixes",
  "description": "Replace generic 'No data' messages with helpful empty states",
  "userStories": [
    {
      "id": "US-001",
      "title": "Add empty state to admin players page",
      "description": "As an admin viewing an empty players list, I want helpful guidance on what to do next.",
      "acceptanceCriteria": [
        "When no players exist, show Empty component",
        "Title: 'No players yet'",
        "Description: 'Get started by adding your first player or importing from CSV'",
        "Action button: 'Add Player' linking to player creation",
        "Type checking passes: npm run check-types"
      ],
      "priority": 1,
      "passes": false,
      "notes": "File: apps/web/src/app/orgs/[orgId]/admin/players/page.tsx"
    },
    {
      "id": "US-002",
      "title": "Add empty state to coach dashboard",
      "description": "As a coach with no assigned teams, I want to know why and what to do.",
      "acceptanceCriteria": [
        "When no teams assigned, show Empty component",
        "Title: 'No teams assigned'",
        "Description: 'You haven't been assigned to any teams yet. Contact your organization admin to get started.'",
        "No action button (coach can't self-assign)",
        "Type checking passes: npm run check-types"
      ],
      "priority": 2,
      "passes": false,
      "notes": "File: apps/web/src/app/orgs/[orgId]/coach/page.tsx"
    },
    {
      "id": "US-003",
      "title": "Add empty state to parent children list",
      "description": "As a parent with no linked children, I want guidance on how to link them.",
      "acceptanceCriteria": [
        "When no children linked, show Empty component",
        "Title: 'No children linked'",
        "Description: 'Contact your organization admin to link your children to your account'",
        "No action button (parent can't self-link)",
        "Type checking passes: npm run check-types"
      ],
      "priority": 3,
      "passes": false,
      "notes": "File: apps/web/src/app/orgs/[orgId]/parents/page.tsx"
    }
  ]
}
